{
  "artifact": {
    "kind": "square",
    "name": "Leaf ",
    "title": "signéh gâx",
    "normalized_title": "signeh gax",
    "meta": {
      "width": 49,
      "height": 49,
      "ms_id": "Sloane 3189",
      "ragged": false,
      "uncertain_marker": "?",
      "sic_marker": "[sic]",
      "lacuna_token": "[LACUNA]",
      "intentionally_empty": "[NULL]",
      "orientation_marker": "^[degrees-clockwise]",
      "contains": [
        "uncertainty_marker",
        "lacuna_token"
      ],
      "notes": ""
    }
  },
  "grid_lines": [
    "z|i|d|l|a|d|a|n|z|o|a|l|c|h|e|p|h|a|c|h|o|d|n|a|c|h|o|n|d|a|l|v|a|h|g|e|h|v|d|n|o|c|h|a|l|a|p|h|a",
    "d|o|x|a|n|b|l|e|h|d|o|n|t|a|l|l|i|g|o|n|c|l|a|m|v|a|c|o|t|h|a|s|c|h|a|d|o|x|y|d|n|a|d|a|b|v|o|l|s",
    "a|r|d|n|o|t|a|m|f|a|l|g|e|t|h|v|d|r|a|d|a|c|l|a|x|a|l|a|n|d|a|x|d|a|i|d|a|c|h|a|m|f|e|d|g|l|o|h|t",
    "c|h|a|n|c|h|a|l|o|n|g|r|a|h|a|d|n|o|c|h|a|n|s|a|d|a|x|v|o|l|s|y|b|l|a|d|a|x|c|o|r|t|a|z|a|n|o|h|a",
    "v|o|l|c|h|i|b|l|a|d|o|x|a|l|d|a|m|p|a|m|c|h|e|p|h|n|e|y|g|o|l|z|a|b|l|a|g|e|o|r|d|e|p|a|g|e|o|l|a",
    "g|o|n|s|e|a|c|h|e|p|h|n|o|c|h|a|n|z|a|a|l|z|a|n|g|e|p|h|l|a|d|o|n|g|e|t|h|a|n|d|v|n|z|a|g|l|a|a|h",
    "n|o|r|g|a|a|b|a|p|h|n|o|x|g|v|b|r|a|h|a|c|h|e|d|n|o|c|h|a|d|a|l|d|a|n|g|a|n|o|x|a|m|n|a|d|a|x|o|l",
    "p|a|r|t|o|c|h|a|l|o|p|z|v|r|a|h|a|c|h|e|n|z|a|h|l|v|z|a|c|h|a|d|a|x|o|d|g|e|n|s|o|c|h|a|d|e|l|v|a",
    "a|m|l|e|m|p|h|a|d|a|n|t|a|g|e|n|e|s|f|r|a|m|s|e|b|l|o|p|a|g|e|d|r|o|b|a|a|l|c|h|a|r|a|x|o|d|a|a|h",
    "p|l|v|t|a|n|t|o|g|a|n|h|a|d|n|a|z|e|m|n|o|t|a|x|v|d|r|a|x|p|l|o|h|g|e|l|g|a|s|r?|o|g|e|n|s|a|n|d|e",
    "p|l|a|t|a|g|n|a|h|v|o|r|s|a|d|n|o|c|h|a|x|a|r|g|e|n|d|o|h|v|o|l|g|e|m|p|h|a|p|r|a|g|n|a|c|h|a|d|s",
    "v|o|l|t|a|n|o|d|a|x|v|a|l|a|d|n|o|x|d|a|d?|z|e|m|p|l|a|n|o|c|a|l|d|o|g|r|a|a|l|b|l|o|h|a|l|b|l|o|x",
    "c|o|x|e|n|d|o|n|a|h|p|l|v|d|a|b|r|a|h|a|b|z|e|n|o|h|a|l|b|r|a|m|m|a|c|h|o|h|a|l|b|l|a|d|a|n|a|b|s",
    "g|e|l|d|o|c|h|a|n|s|l|a|p|h|a|r|m|a|c|l|o|n|a|l|z|e|d|v|a|r|a|g|e|d|n|o|c|h|a|n|s|a|d|n|o|p|h|a|s",
    "v|a|l|t|e|r|i|o|h|a|c|l|a|n|a|x|g|e|d|a|n|t|a|g|n|o|c|h|a|m|v|a|g|e|s|a|r|s|n|o|h|g|e|l|h|o|l|d|a",
    "v|o|b|r|e|d|o|n|a|x|p|e|r|o|d|a|n|z|a|c|h|e|n|z|a|p|l|o|n|f|r|o|n|g|e|y|a|t|a|g|n|o|h|c|h|a|l|a|x",
    "a|n|g|e|m|v|a|c|o|l|a|t|a|f|n|a|c|o|n|g|e|n|d|r|a|h|o|h|a|s|c|h|n|a|l|v|o|l|g|e|p|h|a|l|d|e|z|o|d",
    "z|v|c|h|a|s|t|o|v|a|n|g|e|p|h|e|a|p|l|a|d|a|x|v|r|g|e|n|o|x|a|l|d|e|p|h|a|c|h|a|d|n|a|h|v|a|l|s|o",
    "d|e|v|n|z|a|z|a|d|g|r|a|m|v|l|c|h|a|d|v|o|s|a|n|g|e|f|a|r|d|r|a|n|c|h|a|t|a|l|g|e|p|p|h|e|s|v|d|a",
    "n|a|l|z|e|n|g|e|n|o|t|a|l|g|e|b|r|a|h|c|o|l|c|h|a|d|n|o|d|a|x|a|r|g|a|c|l|o|t|a|n|t|a|n|t|o|z|a|h",
    "v|o|n|g|e|b|l|a|c|h|v|d|a|x|o|c|r|o|p|a|l|p|h|a|g|e|n|s|a|d|o|n|a|y|g|e|m|p|h|d|e|v|a|l|n|a|a|d|o",
    "p|r|o|c|h|a|s|t|o|r|o|n|t|a|n|t|r|a|p|h|e|a|d|c|h|a|n|z|a|a|l|c|h|a|d|a|n|v|o|r|g|e|m|v|e|s|a|d|o",
    "l|e|x|a|r|g|e|o|x|n|a|x|a|r|n|o|l|a|t|a|n|t|o|g|r|a|p|h|g|e|l|d|o|x|a|c|h|e|l|d|o|n|a|t|a|s|l|o|l",
    "p|l|a|c|o|n|a|b|a|m|n|a|c|h|e|m|a|d|r|o|g|a|n|t|a|l|a|t|o|x|a|n|a|x|a|r|c|h|e|p|h|n|a|t|o|x|a|t|o",
    "v|o|l|z|e|d|o|z|a|c|h|a|d|n|a|l|z|i|n|d|a|c|h|a|n|v|a|l|z|e|c|h|a|p|n|a|t|o|l|a|t|a|d|g|m|a|h|o|h",
    "g|e|n|s|a|l|d|a|h|n|i|h|h|o|d|n|a|c|l|a|n|o|b|l|e|d|o|x|a|r|g|e|f|a|h|p|r|o|c|h|i|m|a|n|a|t|a|x|a",
    "v|o|l|g|l|a|n|a|x|t|o|r|y|e|f|e|a|d|n|o|c|h|a|d|a|x|a|l|g|e|p|r|a|g|e|t|h|o|r|n|e|g|e|n|s|o|h|a|a",
    "a|l|c|l|a|d|r|v|x|a|d|n|o|c|l|a|x|v|a|r|n|o|h|c|l|a|n|s|a|g|n|o|c|h|a|s|t|e|r|r|v|d|a|n|z|a|c|h?|o",
    "p|l|a|n|t|a|n|g|l|a|n|o|x|a|r|n|e|d|e?|a|n|t|a|l|g|e|p|h|a|d|r|o|n|z|a|c|h|e|m|v|a|n|t|a|g|e|l|z|a?",
    "n|e|b|v|l|a|g|e|d|n|o|c|h|a|d|n|a|c|h|y|d|o|n|z|a|n|e|c|h|a|s|t|o|r|a|d|n|o|r|b|a|d|c|l|a|n|t|a|[LACUNA]?",
    "v|d|r|a|d|e|n|o|x|a|l|d|a|c|h|a|d|o|n|z|e|d|n|o|c|l|a|p|r|a|g|a|o|c|h|a|p|h|a|n|v|d|r|a|g|e|d|o|[LACUNA]?",
    "c|a|p|a|r|m|a|c|h|a|v|n|z|i|n|o|c|h|a|n|v|a|r|n|o|d|a|n|a|h|v|l|g|e|d|v|a|n|o|x|a|c|r|a|d|o|x|a|[LACUNA]?",
    "p|a|c|l|a|d|m|o|c|o|n|a|d|r|a|n|v|a|g|a|h|v|l|z|i|n|o|c|h|a|n|o|x|a|n|a|d|a|x|o|l|p|h|a|n|e|o|t|[LACUNA]?",
    "v|a|l|h|v|m|a|r|o|n|t|a|n|t|o|x|o|l|g|e|p|h|a|n|a|t|o|x|a|n|c|h|a|n|a|g|e|n|v|a|d|a|h|v|d|n|a|r|b",
    "v|o|r|t|a|n|v|a|h|v|l|g|e|n|s|o|d|a|h|v|n|c|h|e|l|d|o|x|a|p|r|o|c|h|a|p|n|a|g|e|n|z|o|c|l|a|n|o|r",
    "p|h|i|a|l|g|a|d|o|l|z|e|d|n|o|c|h|a|n|s|a|g|n|a|c|h|a|p|h|a|x|a|d|e|b|l|a|h|n|o|l|a|d|n|o|c|h|a|n",
    "z|v|b|l|a|x|v|r|n|o|c|h|a|d|a|n|d|a|l|z|e|a|c|h|y|d|r|a|x|a|c|h|a|d|n|o|x|a|r|m|v|r|a|b|r|a|d|o|h",
    "g|e|m|n|a|s|t|r|o|d|a|c|h|y|l|d|a|n|o|x|a|c|l|a|d|a|p|h|v|r|d|r|a|g|e|n|z|o|c|a|c|a|d|n|a|p|h|e|r",
    "v|l|g|e|n|t|o|g|a|n|z|a|p|a|l|m|e|d|o|n|a|h|v|o|l|t|a|z|a|n|e|x|o|l|d|a|n|e|o|c|h|a|d|a|d|n|o|c|h",
    "a|r|i|n|g|i|t|h|a|c|h|a|r|p|r|a|x|a|d|n|o|c|h|a|h|v|o|r|t|s|a|l|n|a|x|a|d|r|o|n|z|a|c|h|a|n|z|a|b",
    "n|e|v|o|r|n|a|d|a|n|c|h|a|l|d|o|c|h|a|x|v|o|l|t|a|g|l|a|d|a|x|a|r|b|r|a|c|h|a|d|m|a|c|h|e|n|z|o|h",
    "a|l|p|n|l|a|c|h|a|p|h|n|a|t|o|l|a|n|v|a|r|n|a|c|l|a|d|o|x|a|d|a|v|a|n|t|a|g|n|o|c|h|a|l|o|h|a|t?|o",
    "v|o|l|g|i|p|h|e|x|a|r|m|i|i|h|a|d|a|n|t|a|g|n|a|c|h|e|p|h|a|d|n|a|d|a|x|a|l|g|e|n|z|a|c|l|a|d|o|o",
    "n|o|l|z|i|c|h|a|d|n|o|c|h|a|r|o|n|v|o|l|h|a|n|d|a|c|h|a|n|a|b|v|r|a|d|a|b|r|a|h|v|l|z|a|c|h|a|d|o",
    "v|l|z|a|d|n|o|d|a|x|a|l|p|r|a|g|n|a|c|h|a|n|d|o|n|t|a|r|p|h|a|m|p|h|a|n|g|e|t|h|n|o|x|a|l|z|e|d|s",
    "p|r|a|c|h|e|p|h|a|d|r|a|n|t|a|g|e|n|t|a|l|a|n|n|a|t|a|x|a|r|g|e|d|n|o|c|h|a|p|n|o|c|h|e|n|s|o|a|h",
    "z|e|d|a|r|g|a|o|x|a|l|p|v|l|a|b|r|a|n|t|a|x|a|q|v|a|l|z|e|g|o|h|a|l|d|r|a|x|a|v|r|a|n|t|a|h|v|r|o",
    "d|a|n|s|a|g|n|o|c|h|a|n|s|a|l|p|a|l|a|d|v|d|r|a|g|a|h|b|r|a|n|t|o|n|a|x|a|l|g|e|p|h|a|c|h|a|n|z|a",
    "c|h|a|n|t|a|l|z|a|n|a|d|r|a|n|t|o|x|a|p|l|a|g|e|d|a|h|v|o|l|z|i|b|l|a|d|a|x|t|a|n|t|a|f|n|a|c|h|a"
  ]
}